neo/__init__.py
neo/core/__init__.py
neo/core/analogsignal.py
neo/core/baseneo.py
neo/core/basesignal.py
neo/core/block.py
neo/core/container.py
neo/core/dataobject.py
neo/core/epoch.py
neo/core/event.py
neo/core/filters.py
neo/core/group.py
neo/core/imagesequence.py
neo/core/irregularlysampledsignal.py
neo/core/objectlist.py
neo/core/regionofinterest.py
neo/core/segment.py
neo/core/spiketrain.py
neo/core/spiketrainlist.py
neo/core/view.py
neo/io/__init__.py
neo/io/alphaomegaio.py
neo/io/asciiimageio.py
neo/io/asciisignalio.py
neo/io/asciispiketrainio.py
neo/io/axographio.py
neo/io/axonaio.py
neo/io/axonio.py
neo/io/basefromrawio.py
neo/io/baseio.py
neo/io/bci2000io.py
neo/io/biocamio.py
neo/io/blackrockio.py
neo/io/blkio.py
neo/io/brainvisionio.py
neo/io/brainwaredamio.py
neo/io/brainwaref32io.py
neo/io/brainwaresrcio.py
neo/io/cedio.py
neo/io/edfio.py
neo/io/elanio.py
neo/io/elphyio.py
neo/io/exampleio.py
neo/io/igorproio.py
neo/io/intanio.py
neo/io/klustakwikio.py
neo/io/kwikio.py
neo/io/maxwellio.py
neo/io/mearecio.py
neo/io/medio.py
neo/io/micromedio.py
neo/io/neomatlabio.py
neo/io/nestio.py
neo/io/neuralynxio.py
neo/io/neuroexplorerio.py
neo/io/neuronexusio.py
neo/io/neuroscopeio.py
neo/io/neuroshareapiio.py
neo/io/neurosharectypesio.py
neo/io/nixio.py
neo/io/nixio_fr.py
neo/io/nwbio.py
neo/io/openephysbinaryio.py
neo/io/openephysio.py
neo/io/phyio.py
neo/io/pickleio.py
neo/io/plexon2io.py
neo/io/plexonio.py
neo/io/proxyobjects.py
neo/io/rawbinarysignalio.py
neo/io/rawmcsio.py
neo/io/spike2io.py
neo/io/spikegadgetsio.py
neo/io/spikeglxio.py
neo/io/stimfitio.py
neo/io/tdtio.py
neo/io/tiffio.py
neo/io/tools.py
neo/io/winedrio.py
neo/io/winwcpio.py
neo/rawio/__init__.py
neo/rawio/alphaomegarawio.py
neo/rawio/axographrawio.py
neo/rawio/axonarawio.py
neo/rawio/axonrawio.py
neo/rawio/baserawio.py
neo/rawio/bci2000rawio.py
neo/rawio/biocamrawio.py
neo/rawio/blackrockrawio.py
neo/rawio/brainvisionrawio.py
neo/rawio/cedrawio.py
neo/rawio/edfrawio.py
neo-0.14.2.dist-info/licenses/AUTHORS
neo-0.14.2.dist-info/licenses/LICENSE.txt
neo-0.14.2.dist-info/METADATA
neo-0.14.2.dist-info/WHEEL
neo-0.14.2.dist-info/top_level.txt
neo-0.14.2.dist-info/RECORD
