Metadata-Version: 2.4
Name: neo
Version: 0.14.2
Summary: Neo is a package for representing electrophysiology data in Python, together with support for reading a wide range of neurophysiology file formats
Author: Neo authors and contributors
License: BSD 3-Clause License
Project-URL: homepage, https://neuralensemble.org/neo
Project-URL: documentation, http://neo.readthedocs.io/
Project-URL: repository, https://github.com/NeuralEnsemble/python-neo
Project-URL: download, http://pypi.python.org/pypi/neo
Classifier: Development Status :: 4 - Beta
Classifier: Programming Language :: Python :: 3
Classifier: Operating System :: OS Independent
Classifier: Intended Audience :: Science/Research
Classifier: Natural Language :: English
Classifier: Topic :: Scientific/Engineering
Classifier: License :: OSI Approved :: BSD License
Classifier: Programming Language :: Python :: 3.9
Classifier: Programming Language :: Python :: 3.10
Classifier: Programming Language :: Python :: 3.11
Classifier: Programming Language :: Python :: 3.12
Classifier: Programming Language :: Python :: 3.13
Classifier: Programming Language :: Python :: 3 :: Only
Requires-Python: >=3.9
License-File: LICENSE.txt
License-File: AUTHORS
Requires-Dist: packaging
Requires-Dist: numpy>=1.24.4
Requires-Dist: quantities>=0.16.1
Provides-Extra: iocache
Requires-Dist: joblib>=1.0.0; extra == "iocache"
Provides-Extra: test
Requires-Dist: pytest; extra == "test"
Requires-Dist: pytest-cov; extra == "test"
Requires-Dist: datalad; extra == "test"
Requires-Dist: scipy>=1.0.0; extra == "test"
Requires-Dist: pyedflib; extra == "test"
Requires-Dist: h5py; extra == "test"
Requires-Dist: igor2; extra == "test"
Requires-Dist: klusta; extra == "test"
Requires-Dist: tqdm; extra == "test"
Requires-Dist: nixio; extra == "test"
Requires-Dist: matplotlib; extra == "test"
Requires-Dist: ipython; extra == "test"
Requires-Dist: joblib>=1.0.0; extra == "test"
Requires-Dist: coverage; extra == "test"
Requires-Dist: coveralls; extra == "test"
Requires-Dist: pillow; extra == "test"
Requires-Dist: sonpy; python_version < "3.10" and extra == "test"
Requires-Dist: pynwb; extra == "test"
Requires-Dist: probeinterface; extra == "test"
Requires-Dist: zugbruecke>=0.2; extra == "test"
Requires-Dist: wenv; extra == "test"
Provides-Extra: docs
Requires-Dist: docutils; extra == "docs"
Requires-Dist: sphinx; extra == "docs"
Requires-Dist: sphinx-inline-tabs; extra == "docs"
Requires-Dist: sphinx-gallery; extra == "docs"
Requires-Dist: pydata-sphinx-theme; extra == "docs"
Requires-Dist: sphinx-design; extra == "docs"
Requires-Dist: ipython; extra == "docs"
Requires-Dist: matplotlib; extra == "docs"
Requires-Dist: nixio; extra == "docs"
Requires-Dist: pynwb; extra == "docs"
Requires-Dist: igor2; extra == "docs"
Requires-Dist: numpy>=2.0; extra == "docs"
Provides-Extra: dev
Requires-Dist: build; extra == "dev"
Requires-Dist: twine; extra == "dev"
Requires-Dist: black; extra == "dev"
Provides-Extra: igorproio
Requires-Dist: igor2; extra == "igorproio"
Provides-Extra: kwikio
Requires-Dist: klusta; extra == "kwikio"
Provides-Extra: neomatlabio
Requires-Dist: scipy>=1.0.0; extra == "neomatlabio"
Provides-Extra: nixio
Requires-Dist: nixio>=1.5.0; extra == "nixio"
Provides-Extra: tiffio
Requires-Dist: pillow; extra == "tiffio"
Provides-Extra: edf
Requires-Dist: pyedflib; extra == "edf"
Provides-Extra: ced
Requires-Dist: sonpy; extra == "ced"
Provides-Extra: nwb
Requires-Dist: pynwb; extra == "nwb"
Provides-Extra: maxwell
Requires-Dist: h5py; extra == "maxwell"
Provides-Extra: biocam
Requires-Dist: h5py; extra == "biocam"
Provides-Extra: med
Requires-Dist: dhn_med_py<2.0; extra == "med"
Provides-Extra: plexon2
Requires-Dist: zugbruecke>=0.2; sys_platform != "win32" and extra == "plexon2"
Requires-Dist: wenv; sys_platform != "win32" and extra == "plexon2"
Provides-Extra: neuralynx
Requires-Dist: python-dateutil; extra == "neuralynx"
Provides-Extra: all
Requires-Dist: coverage; extra == "all"
Requires-Dist: coveralls; extra == "all"
Requires-Dist: h5py; extra == "all"
Requires-Dist: igor2; extra == "all"
Requires-Dist: ipython; extra == "all"
Requires-Dist: joblib>=1.0.0; extra == "all"
Requires-Dist: klusta; extra == "all"
Requires-Dist: matplotlib; extra == "all"
Requires-Dist: nixio>=1.5.0; extra == "all"
Requires-Dist: pillow; extra == "all"
Requires-Dist: probeinterface; extra == "all"
Requires-Dist: pyedflib; extra == "all"
Requires-Dist: pynwb; extra == "all"
Requires-Dist: pytest; extra == "all"
Requires-Dist: pytest-cov; extra == "all"
Requires-Dist: scipy>=1.0.0; extra == "all"
Requires-Dist: sonpy; extra == "all"
Requires-Dist: tqdm; extra == "all"
Requires-Dist: wenv; sys_platform != "win32" and extra == "all"
Requires-Dist: zugbruecke>=0.2; sys_platform != "win32" and extra == "all"
Requires-Dist: python-dateutil; extra == "all"
Dynamic: license-file
